python_hugo/__init__.py
python_hugo/cli.py
python_hugo/binaries/.gitignore
python_hugo/binaries/hugo-0.121.2-linux-arm64
python_hugo-24.1.1.dist-info/LICENSE
python_hugo-24.1.1.dist-info/METADATA
python_hugo-24.1.1.dist-info/WHEEL
python_hugo-24.1.1.dist-info/entry_points.txt
python_hugo-24.1.1.dist-info/top_level.txt
python_hugo-24.1.1.dist-info/RECORD
