Metadata-Version: 2.1
Name: python-hugo
Version: 24.1.1
Summary: Binaries for the Hugo static site generator, installable with pip
Author-email: Agriya Khetarpal <agriyakhetarpal@outlook.com>
Maintainer-email: Agriya Khetarpal <agriyakhetarpal@outlook.com>
License: Apache License v2.0
Project-URL: Homepage, https://github.com/agriyakhetarpal/hugo-python-distributions
Project-URL: Issues, https://github.com/agriyakhetarpal/hugo-python-distributions/issues
Project-URL: Changelog, https://github.com/agriyakhetarpal/hugo-python-distributions/releases
Classifier: Development Status :: 3 - Alpha
Classifier: Intended Audience :: Developers
Classifier: Intended Audience :: Information Technology
Classifier: License :: OSI Approved :: Apache Software License
Classifier: Operating System :: Unix
Classifier: Operating System :: MacOS
Classifier: Operating System :: Microsoft :: Windows
Classifier: Programming Language :: Go
Classifier: Programming Language :: Python
Classifier: Programming Language :: Python :: 3
Classifier: Programming Language :: Python :: 3 :: Only
Classifier: Programming Language :: Python :: 3.8
Classifier: Programming Language :: Python :: 3.9
Classifier: Programming Language :: Python :: 3.10
Classifier: Programming Language :: Python :: 3.11
Classifier: Programming Language :: Python :: 3.12
Classifier: Topic :: Internet
Classifier: Topic :: Internet :: WWW/HTTP :: Dynamic Content :: Content Management System
Classifier: Topic :: Internet :: WWW/HTTP :: Browsers
Classifier: Topic :: Utilities
Requires-Python: <3.13,>=3.8
License-File: LICENSE
